examples/__init__.py
examples/console/__init__.py
examples/console/__main__.py
examples/console/console.py
examples/console/handlers.py
examples/mcp-servers/reddit-sentiment/__init__.py
examples/mcp-servers/reddit-sentiment/__main__.py
examples/mcp-servers/reddit-sentiment/reddit_sentiment.py
third_party/xmlable/__init__.py
third_party/xmlable/_errors.py
third_party/xmlable/_io.py
third_party/xmlable/_lxml_helpers.py
third_party/xmlable/_manual.py
third_party/xmlable/_user.py
third_party/xmlable/_utils.py
third_party/xmlable/_xmlify.py
third_party/xmlable/_xobject.py
third_party/xmlable/py.typed
xml_pipeline/__init__.py
xml_pipeline/cli.py
xml_pipeline/config/__init__.py
xml_pipeline/config/agents.py
xml_pipeline/config/features.py
xml_pipeline/config/loader.py
xml_pipeline/config/split_loader.py
xml_pipeline/config/template.py
xml_pipeline/config/listeners/__init__.py
xml_pipeline/config/listeners/store.py
xml_pipeline/config/schema/__init__.py
xml_pipeline/config/schema/listener.py
xml_pipeline/config/schema/organism.py
xml_pipeline/listeners/__init__.py
xml_pipeline/listeners/llm_connection.py
xml_pipeline/listeners/llm_listener.py
xml_pipeline/listeners/wasm_listener.py
xml_pipeline/listeners/examples/__init__.py
xml_pipeline/listeners/examples/echo_chamber.py
xml_pipeline/listeners/examples/grok_personality.py
xml_pipeline/llm/__init__.py
xml_pipeline/llm/backend.py
xml_pipeline/llm/router.py
xml_pipeline/llm/token_bucket.py
xml_pipeline/memory/__init__.py
xml_pipeline/memory/context_buffer.py
xml_pipeline/message_bus/__init__.py
xml_pipeline/message_bus/config.py
xml_pipeline/message_bus/envelope.py
xml_pipeline/message_bus/errors.py
xml_pipeline/message_bus/message_state.py
xml_pipeline/message_bus/scheduler.py
xml_pipeline/message_bus/stream_pump.py
xml_pipeline/message_bus/system_pipeline.py
xml_pipeline/message_bus/thread.py
xml_pipeline/message_bus/thread_registry.py
xml_pipeline/message_bus/todo_registry.py
xml_pipeline/message_bus/steps/__init__.py
xml_pipeline-0.4.0.dist-info/licenses/LICENSE
xml_pipeline-0.4.0.dist-info/METADATA
xml_pipeline-0.4.0.dist-info/WHEEL
xml_pipeline-0.4.0.dist-info/entry_points.txt
xml_pipeline-0.4.0.dist-info/top_level.txt
xml_pipeline-0.4.0.dist-info/RECORD
