Metadata-Version: 2.4
Name: xml-pipeline
Version: 0.4.0
Summary: Schema-driven XML message bus for multi-agent systems
Author: xml-pipeline contributors
License: MIT
Project-URL: Homepage, https://xml-pipeline.org
Project-URL: Documentation, https://xml-pipeline.org/docs
Project-URL: Repository, https://git.xml-pipeline.org/dullfig/xml-pipeline
Project-URL: Issues, https://git.xml-pipeline.org/dullfig/xml-pipeline/issues
Keywords: xml,multi-agent,message-bus,llm,pipeline,async
Classifier: Development Status :: 4 - Beta
Classifier: Intended Audience :: Developers
Classifier: License :: OSI Approved :: MIT License
Classifier: Programming Language :: Python :: 3
Classifier: Programming Language :: Python :: 3.11
Classifier: Programming Language :: Python :: 3.12
Classifier: Programming Language :: Python :: 3.13
Classifier: Framework :: AsyncIO
Classifier: Topic :: Software Development :: Libraries :: Python Modules
Classifier: Topic :: System :: Distributed Computing
Requires-Python: >=3.11
License-File: LICENSE
Requires-Dist: lxml>=4.9
Requires-Dist: aiostream>=0.5
Requires-Dist: pyyaml>=6.0
Requires-Dist: pyhumps>=3.0
Requires-Dist: cryptography>=41.0
Requires-Dist: httpx>=0.27
Requires-Dist: termcolor>=2.0
Provides-Extra: anthropic
Requires-Dist: anthropic>=0.39; extra == "anthropic"
Provides-Extra: openai
Requires-Dist: openai>=1.0; extra == "openai"
Provides-Extra: redis
Requires-Dist: redis>=5.0; extra == "redis"
Provides-Extra: search
Requires-Dist: duckduckgo-search>=6.0; extra == "search"
Provides-Extra: console
Requires-Dist: prompt_toolkit>=3.0; extra == "console"
Provides-Extra: llm
Requires-Dist: xml-pipeline[anthropic,openai]; extra == "llm"
Provides-Extra: tools
Requires-Dist: xml-pipeline[redis,search]; extra == "tools"
Provides-Extra: all
Requires-Dist: xml-pipeline[console,llm,tools]; extra == "all"
Provides-Extra: test
Requires-Dist: pytest>=7.0; extra == "test"
Requires-Dist: pytest-asyncio>=0.23; extra == "test"
Requires-Dist: pytest-cov>=4.0; extra == "test"
Provides-Extra: dev
Requires-Dist: xml-pipeline[all,test]; extra == "dev"
Requires-Dist: mypy>=1.8; extra == "dev"
Requires-Dist: ruff>=0.1; extra == "dev"
Requires-Dist: types-PyYAML; extra == "dev"
Dynamic: license-file
